fsm-assignments/  problem1_seqdet/seq_detect_mealy.v
module seq_detect_mealy (
 input wire clk,
 input wire rst, //syncactive-high
 input wire din, //serialinputbitperclock
 output wire y //1-cyclepulsewhenpattern...1101seen
 );
   
    localparam S0   = 2'b00,
               S1   = 2'b01,
               S2   = 2'b10,
               S3   = 2'b11;

    reg [1:0] state, next_state;

    // next-state 
    always @(*) begin
        
        case (state)
            S0: begin
                if (din)     next_state = S1;
                else         next_state = S0;
            end
            S1: begin
                if (din)     next_state = S2;
                else         next_state = S0;
            end
            S2: begin
                if (din)     next_state = S2; 
                else         next_state = S3;
            end
            S3: begin
                if (din)     next_state = S1;  
                else         next_state = S0;
            end
            default: next_state = S0;
        endcase
    end

    
    always @(posedge clk) begin
        if (rst)
            state <= S0;
        else
            state <= next_state;
    end

   
    assign y = (state == S3) & din;

endmodule

fsm-assignments/  problem1_seqdet/tb_seq_detect_mealy.v
module tb_seq_detect_mealy;
reg clk,rst,din;
wire y;

 seq_detect_mealy dut(.clk(clk),
                      .rst(rst),
                      .din(din),
                       .y(y));

reg [15:0] sequence = 16'b1101101101011001; 
integer i;


initial clk = 0;
    always #5 clk = ~clk;
 
initial begin
       
$dumpfile("dump.vcd");
$dumpvars(0, tb_seq_detect_mealy);

    
    rst = 1; din = 0;
    @(posedge clk);
    rst = 0;

    
    for (i = 15; i >= 0; i = i - 1) begin
            din = sequence[i];
            @(posedge clk);
    end

$finish;
end


initial begin
        $display("time   clk din y");
        $monitor("%4t   %b   %b   %b", $time, clk, din, y);
    end
endmodule

fsm-assignments/  problem1_seqdet/dump.vcd
$date
	Sun Aug 17 16:06:38 2025
$end
$version
	Icarus Verilog
$end
$timescale
	1s
$end
$scope module tb_seq_detect_mealy $end
$var wire 1 ! y $end
$var reg 1 " clk $end
$var reg 1 # din $end
$var reg 1 $ rst $end
$var reg 16 % sequence [15:0] $end
$var integer 32 & i [31:0] $end
$scope module dut $end
$var wire 1 " clk $end
$var wire 1 # din $end
$var wire 1 $ rst $end
$var wire 1 ! y $end
$var parameter 2 ' S0 $end
$var parameter 2 ( S1 $end
$var parameter 2 ) S2 $end
$var parameter 2 * S3 $end
$var reg 2 + next_state [1:0] $end
$var reg 2 , state [1:0] $end
$upscope $end
$upscope $end
$enddefinitions $end
$comment Show the parameter values. $end
$dumpall
b11 *
b10 )
b1 (
b0 '
$end
#0
$dumpvars
bx ,
b0 +
bx &
b1101101101011001 %
1$
0#
0"
0!
$end
#5
b1 +
b0 ,
0!
1#
b1111 &
0$
1"
#10
0"
#15
b10 +
b1 ,
b1110 &
1"
#20
0"
#25
b10 ,
b11 +
0#
b1101 &
1"
#30
0"
#35
1!
b11 ,
b1 +
1#
b1100 &
1"
#40
0"
#45
b10 +
0!
b1 ,
b1011 &
1"
#50
0"
#55
b10 ,
b11 +
0#
b1010 &
1"
#60
0"
#65
1!
b11 ,
b1 +
1#
b1001 &
1"
#70
0"
#75
b10 +
0!
b1 ,
b1000 &
1"
#80
0"
#85
b10 ,
b11 +
0#
b111 &
1"
#90
0"
#95
1!
b11 ,
b1 +
1#
b110 &
1"
#100
0"
#105
b1 ,
0!
b0 +
0#
b101 &
1"
#110
0"
#115
b0 ,
b1 +
1#
b100 &
1"
#120
0"
#125
b10 +
b1 ,
b11 &
1"
#130
0"
#135
b10 ,
b11 +
0#
b10 &
1"
#140
0"
#145
b0 +
b11 ,
b1 &
1"
#150
0"
#155
b0 ,
0!
b1 +
1#
b0 &
1"
#160
0"
#165
b10 +
b1 ,
b11111111111111111111111111111111 &
1"
