LAB1/Design2/equality_comparator.v
module equality_comparator(
input [3:0] A,
input [3:0] B,
output O

);

wire [3:0] temp;

assign temp = ~(A ^ B);   
assign O = &temp;     

endmodule

LAB1/Design2/equality_comparator_tb.v
`timescale 1ns/1ns
`include "equality_comparator.v"

module equality_comparator_tb;

    reg [3:0] a, b;
    wire o;

    equality_comparator comp (
        .A(a),
        .B(b),
        .O(o)
    );
    integer i,j;
    initial 
    begin
        $dumpfile("equality_comparator.vcd");
        $dumpvars(0, equality_comparator_tb);

      /*  A = 4'b0000; B = 4'b0000; 
        #10;

        A = 4'b0001; B = 4'b0000; 
        #10;

        A = 4'b1010; B = 4'b1010;
        #10;

        A = 4'b1111; B = 4'b0000; 
        #10;

        A = 4'b1100; B = 4'b1001; 
        #10;

        A = 4'b0110; B = 4'b0110; 
        #10;*/

            for (i = 0; i < 16; i = i + 1) begin
            for (j = 0; j < 16; j = j + 1) begin
                a= i[3:0];
                b = j[3:0];
                #10;

            end
            end

        $finish;
    end
endmodule

LAB1/Design2/equality_comparator.vcd
$date
	Wed Jul 30 22:00:12 2025
$end
$version
	Icarus Verilog
$end
$timescale
	1ns
$end
$scope module equality_comparator_tb $end
$var wire 1 ! o $end
$var reg 4 " a [3:0] $end
$var reg 4 # b [3:0] $end
$var integer 32 $ i [31:0] $end
$var integer 32 % j [31:0] $end
$scope module comp $end
$var wire 4 & A [3:0] $end
$var wire 4 ' B [3:0] $end
$var wire 4 ( temp [3:0] $end
$var wire 1 ! O $end
$upscope $end
$upscope $end
$enddefinitions $end
$comment Show the parameter values. $end
$dumpall
$end
#0
$dumpvars
b1111 (
b0 '
b0 &
b0 %
b0 $
b0 #
b0 "
1!
$end
#10
0!
b1110 (
b1 #
b1 '
b1 %
#20
b1101 (
b10 #
b10 '
b10 %
#30
b1100 (
b11 #
b11 '
b11 %
#40
b1011 (
b100 #
b100 '
b100 %
#50
b1010 (
b101 #
b101 '
b101 %
#60
b1001 (
b110 #
b110 '
b110 %
#70
b1000 (
b111 #
b111 '
b111 %
#80
b111 (
b1000 #
b1000 '
b1000 %
#90
b110 (
b1001 #
b1001 '
b1001 %
#100
b101 (
b1010 #
b1010 '
b1010 %
#110
b100 (
b1011 #
b1011 '
b1011 %
#120
b11 (
b1100 #
b1100 '
b1100 %
#130
b10 (
b1101 #
b1101 '
b1101 %
#140
b1 (
b1110 #
b1110 '
b1110 %
#150
b0 (
b1111 #
b1111 '
b1111 %
#160
b1110 (
b0 #
b0 '
b1 "
b1 &
b1 $
b0 %
#170
1!
b1111 (
b1 #
b1 '
b1 %
#180
0!
b1100 (
b10 #
b10 '
b10 %
#190
b1101 (
b11 #
b11 '
b11 %
#200
b1010 (
b100 #
b100 '
b100 %
#210
b1011 (
b101 #
b101 '
b101 %
#220
b1000 (
b110 #
b110 '
b110 %
#230
b1001 (
b111 #
b111 '
b111 %
#240
b110 (
b1000 #
b1000 '
b1000 %
#250
b111 (
b1001 #
b1001 '
b1001 %
#260
b100 (
b1010 #
b1010 '
b1010 %
#270
b101 (
b1011 #
b1011 '
b1011 %
#280
b10 (
b1100 #
b1100 '
b1100 %
#290
b11 (
b1101 #
b1101 '
b1101 %
#300
b0 (
b1110 #
b1110 '
b1110 %
#310
b1 (
b1111 #
b1111 '
b1111 %
#320
b1101 (
b0 #
b0 '
b10 "
b10 &
b10 $
b0 %
#330
b1100 (
b1 #
b1 '
b1 %
#340
1!
b1111 (
b10 #
b10 '
b10 %
#350
0!
b1110 (
b11 #
b11 '
b11 %
#360
b1001 (
b100 #
b100 '
b100 %
#370
b1000 (
b101 #
b101 '
b101 %
#380
b1011 (
b110 #
b110 '
b110 %
#390
b1010 (
b111 #
b111 '
b111 %
#400
b101 (
b1000 #
b1000 '
b1000 %
#410
b100 (
b1001 #
b1001 '
b1001 %
#420
b111 (
b1010 #
b1010 '
b1010 %
#430
b110 (
b1011 #
b1011 '
b1011 %
#440
b1 (
b1100 #
b1100 '
b1100 %
#450
b0 (
b1101 #
b1101 '
b1101 %
#460
b11 (
b1110 #
b1110 '
b1110 %
#470
b10 (
b1111 #
b1111 '
b1111 %
#480
b1100 (
b0 #
b0 '
b11 "
b11 &
b11 $
b0 %
#490
b1101 (
b1 #
b1 '
b1 %
#500
b1110 (
b10 #
b10 '
b10 %
#510
1!
b1111 (
b11 #
b11 '
b11 %
#520
0!
b1000 (
b100 #
b100 '
b100 %
#530
b1001 (
b101 #
b101 '
b101 %
#540
b1010 (
b110 #
b110 '
b110 %
#550
b1011 (
b111 #
b111 '
b111 %
#560
b100 (
b1000 #
b1000 '
b1000 %
#570
b101 (
b1001 #
b1001 '
b1001 %
#580
b110 (
b1010 #
b1010 '
b1010 %
#590
b111 (
b1011 #
b1011 '
b1011 %
#600
b0 (
b1100 #
b1100 '
b1100 %
#610
b1 (
b1101 #
b1101 '
b1101 %
#620
b10 (
b1110 #
b1110 '
b1110 %
#630
b11 (
b1111 #
b1111 '
b1111 %
#640
b1011 (
b0 #
b0 '
b100 "
b100 &
b100 $
b0 %
#650
b1010 (
b1 #
b1 '
b1 %
#660
b1001 (
b10 #
b10 '
b10 %
#670
b1000 (
b11 #
b11 '
b11 %
#680
1!
b1111 (
b100 #
b100 '
b100 %
#690
0!
b1110 (
b101 #
b101 '
b101 %
#700
b1101 (
b110 #
b110 '
b110 %
#710
b1100 (
b111 #
b111 '
b111 %
#720
b11 (
b1000 #
b1000 '
b1000 %
#730
b10 (
b1001 #
b1001 '
b1001 %
#740
b1 (
b1010 #
b1010 '
b1010 %
#750
b0 (
b1011 #
b1011 '
b1011 %
#760
b111 (
b1100 #
b1100 '
b1100 %
#770
b110 (
b1101 #
b1101 '
b1101 %
#780
b101 (
b1110 #
b1110 '
b1110 %
#790
b100 (
b1111 #
b1111 '
b1111 %
#800
b1010 (
b0 #
b0 '
b101 "
b101 &
b101 $
b0 %
#810
b1011 (
b1 #
b1 '
b1 %
#820
b1000 (
b10 #
b10 '
b10 %
#830
b1001 (
b11 #
b11 '
b11 %
#840
b1110 (
b100 #
b100 '
b100 %
#850
1!
b1111 (
b101 #
b101 '
b101 %
#860
0!
b1100 (
b110 #
b110 '
b110 %
#870
b1101 (
b111 #
b111 '
b111 %
#880
b10 (
b1000 #
b1000 '
b1000 %
#890
b11 (
b1001 #
b1001 '
b1001 %
#900
b0 (
b1010 #
b1010 '
b1010 %
#910
b1 (
b1011 #
b1011 '
b1011 %
#920
b110 (
b1100 #
b1100 '
b1100 %
#930
b111 (
b1101 #
b1101 '
b1101 %
#940
b100 (
b1110 #
b1110 '
b1110 %
#950
b101 (
b1111 #
b1111 '
b1111 %
#960
b1001 (
b0 #
b0 '
b110 "
b110 &
b110 $
b0 %
#970
b1000 (
b1 #
b1 '
b1 %
#980
b1011 (
b10 #
b10 '
b10 %
#990
b1010 (
b11 #
b11 '
b11 %
#1000
b1101 (
b100 #
b100 '
b100 %
#1010
b1100 (
b101 #
b101 '
b101 %
#1020
1!
b1111 (
b110 #
b110 '
b110 %
#1030
0!
b1110 (
b111 #
b111 '
b111 %
#1040
b1 (
b1000 #
b1000 '
b1000 %
#1050
b0 (
b1001 #
b1001 '
b1001 %
#1060
b11 (
b1010 #
b1010 '
b1010 %
#1070
b10 (
b1011 #
b1011 '
b1011 %
#1080
b101 (
b1100 #
b1100 '
b1100 %
#1090
b100 (
b1101 #
b1101 '
b1101 %
#1100
b111 (
b1110 #
b1110 '
b1110 %
#1110
b110 (
b1111 #
b1111 '
b1111 %
#1120
b1000 (
b0 #
b0 '
b111 "
b111 &
b111 $
b0 %
#1130
b1001 (
b1 #
b1 '
b1 %
#1140
b1010 (
b10 #
b10 '
b10 %
#1150
b1011 (
b11 #
b11 '
b11 %
#1160
b1100 (
b100 #
b100 '
b100 %
#1170
b1101 (
b101 #
b101 '
b101 %
#1180
b1110 (
b110 #
b110 '
b110 %
#1190
1!
b1111 (
b111 #
b111 '
b111 %
#1200
0!
b0 (
b1000 #
b1000 '
b1000 %
#1210
b1 (
b1001 #
b1001 '
b1001 %
#1220
b10 (
b1010 #
b1010 '
b1010 %
#1230
b11 (
b1011 #
b1011 '
b1011 %
#1240
b100 (
b1100 #
b1100 '
b1100 %
#1250
b101 (
b1101 #
b1101 '
b1101 %
#1260
b110 (
b1110 #
b1110 '
b1110 %
#1270
b111 (
b1111 #
b1111 '
b1111 %
#1280
b0 #
b0 '
b1000 "
b1000 &
b1000 $
b0 %
#1290
b110 (
b1 #
b1 '
b1 %
#1300
b101 (
b10 #
b10 '
b10 %
#1310
b100 (
b11 #
b11 '
b11 %
#1320
b11 (
b100 #
b100 '
b100 %
#1330
b10 (
b101 #
b101 '
b101 %
#1340
b1 (
b110 #
b110 '
b110 %
#1350
b0 (
b111 #
b111 '
b111 %
#1360
1!
b1111 (
b1000 #
b1000 '
b1000 %
#1370
0!
b1110 (
b1001 #
b1001 '
b1001 %
#1380
b1101 (
b1010 #
b1010 '
b1010 %
#1390
b1100 (
b1011 #
b1011 '
b1011 %
#1400
b1011 (
b1100 #
b1100 '
b1100 %
#1410
b1010 (
b1101 #
b1101 '
b1101 %
#1420
b1001 (
b1110 #
b1110 '
b1110 %
#1430
b1000 (
b1111 #
b1111 '
b1111 %
#1440
b110 (
b0 #
b0 '
b1001 "
b1001 &
b1001 $
b0 %
#1450
b111 (
b1 #
b1 '
b1 %
#1460
b100 (
b10 #
b10 '
b10 %
#1470
b101 (
b11 #
b11 '
b11 %
#1480
b10 (
b100 #
b100 '
b100 %
#1490
b11 (
b101 #
b101 '
b101 %
#1500
b0 (
b110 #
b110 '
b110 %
#1510
b1 (
b111 #
b111 '
b111 %
#1520
b1110 (
b1000 #
b1000 '
b1000 %
#1530
1!
b1111 (
b1001 #
b1001 '
b1001 %
#1540
0!
b1100 (
b1010 #
b1010 '
b1010 %
#1550
b1101 (
b1011 #
b1011 '
b1011 %
#1560
b1010 (
b1100 #
b1100 '
b1100 %
#1570
b1011 (
b1101 #
b1101 '
b1101 %
#1580
b1000 (
b1110 #
b1110 '
b1110 %
#1590
b1001 (
b1111 #
b1111 '
b1111 %
#1600
b101 (
b0 #
b0 '
b1010 "
b1010 &
b1010 $
b0 %
#1610
b100 (
b1 #
b1 '
b1 %
#1620
b111 (
b10 #
b10 '
b10 %
#1630
b110 (
b11 #
b11 '
b11 %
#1640
b1 (
b100 #
b100 '
b100 %
#1650
b0 (
b101 #
b101 '
b101 %
#1660
b11 (
b110 #
b110 '
b110 %
#1670
b10 (
b111 #
b111 '
b111 %
#1680
b1101 (
b1000 #
b1000 '
b1000 %
#1690
b1100 (
b1001 #
b1001 '
b1001 %
#1700
1!
b1111 (
b1010 #
b1010 '
b1010 %
#1710
0!
b1110 (
b1011 #
b1011 '
b1011 %
#1720
b1001 (
b1100 #
b1100 '
b1100 %
#1730
b1000 (
b1101 #
b1101 '
b1101 %
#1740
b1011 (
b1110 #
b1110 '
b1110 %
#1750
b1010 (
b1111 #
b1111 '
b1111 %
#1760
b100 (
b0 #
b0 '
b1011 "
b1011 &
b1011 $
b0 %
#1770
b101 (
b1 #
b1 '
b1 %
#1780
b110 (
b10 #
b10 '
b10 %
#1790
b111 (
b11 #
b11 '
b11 %
#1800
b0 (
b100 #
b100 '
b100 %
#1810
b1 (
b101 #
b101 '
b101 %
#1820
b10 (
b110 #
b110 '
b110 %
#1830
b11 (
b111 #
b111 '
b111 %
#1840
b1100 (
b1000 #
b1000 '
b1000 %
#1850
b1101 (
b1001 #
b1001 '
b1001 %
#1860
b1110 (
b1010 #
b1010 '
b1010 %
#1870
1!
b1111 (
b1011 #
b1011 '
b1011 %
#1880
0!
b1000 (
b1100 #
b1100 '
b1100 %
#1890
b1001 (
b1101 #
b1101 '
b1101 %
#1900
b1010 (
b1110 #
b1110 '
b1110 %
#1910
b1011 (
b1111 #
b1111 '
b1111 %
#1920
b11 (
b0 #
b0 '
b1100 "
b1100 &
b1100 $
b0 %
#1930
b10 (
b1 #
b1 '
b1 %
#1940
b1 (
b10 #
b10 '
b10 %
#1950
b0 (
b11 #
b11 '
b11 %
#1960
b111 (
b100 #
b100 '
b100 %
#1970
b110 (
b101 #
b101 '
b101 %
#1980
b101 (
b110 #
b110 '
b110 %
#1990
b100 (
b111 #
b111 '
b111 %
#2000
b1011 (
b1000 #
b1000 '
b1000 %
#2010
b1010 (
b1001 #
b1001 '
b1001 %
#2020
b1001 (
b1010 #
b1010 '
b1010 %
#2030
b1000 (
b1011 #
b1011 '
b1011 %
#2040
1!
b1111 (
b1100 #
b1100 '
b1100 %
#2050
0!
b1110 (
b1101 #
b1101 '
b1101 %
#2060
b1101 (
b1110 #
b1110 '
b1110 %
#2070
b1100 (
b1111 #
b1111 '
b1111 %
#2080
b10 (
b0 #
b0 '
b1101 "
b1101 &
b1101 $
b0 %
#2090
b11 (
b1 #
b1 '
b1 %
#2100
b0 (
b10 #
b10 '
b10 %
#2110
b1 (
b11 #
b11 '
b11 %
#2120
b110 (
b100 #
b100 '
b100 %
#2130
b111 (
b101 #
b101 '
b101 %
#2140
b100 (
b110 #
b110 '
b110 %
#2150
b101 (
b111 #
b111 '
b111 %
#2160
b1010 (
b1000 #
b1000 '
b1000 %
#2170
b1011 (
b1001 #
b1001 '
b1001 %
#2180
b1000 (
b1010 #
b1010 '
b1010 %
#2190
b1001 (
b1011 #
b1011 '
b1011 %
#2200
b1110 (
b1100 #
b1100 '
b1100 %
#2210
1!
b1111 (
b1101 #
b1101 '
b1101 %
#2220
0!
b1100 (
b1110 #
b1110 '
b1110 %
#2230
b1101 (
b1111 #
b1111 '
b1111 %
#2240
b1 (
b0 #
b0 '
b1110 "
b1110 &
b1110 $
b0 %
#2250
b0 (
b1 #
b1 '
b1 %
#2260
b11 (
b10 #
b10 '
b10 %
#2270
b10 (
b11 #
b11 '
b11 %
#2280
b101 (
b100 #
b100 '
b100 %
#2290
b100 (
b101 #
b101 '
b101 %
#2300
b111 (
b110 #
b110 '
b110 %
#2310
b110 (
b111 #
b111 '
b111 %
#2320
b1001 (
b1000 #
b1000 '
b1000 %
#2330
b1000 (
b1001 #
b1001 '
b1001 %
#2340
b1011 (
b1010 #
b1010 '
b1010 %
#2350
b1010 (
b1011 #
b1011 '
b1011 %
#2360
b1101 (
b1100 #
b1100 '
b1100 %
#2370
b1100 (
b1101 #
b1101 '
b1101 %
#2380
1!
b1111 (
b1110 #
b1110 '
b1110 %
#2390
0!
b1110 (
b1111 #
b1111 '
b1111 %
#2400
b0 (
b0 #
b0 '
b1111 "
b1111 &
b1111 $
b0 %
#2410
b1 (
b1 #
b1 '
b1 %
#2420
b10 (
b10 #
b10 '
b10 %
#2430
b11 (
b11 #
b11 '
b11 %
#2440
b100 (
b100 #
b100 '
b100 %
#2450
b101 (
b101 #
b101 '
b101 %
#2460
b110 (
b110 #
b110 '
b110 %
#2470
b111 (
b111 #
b111 '
b111 %
#2480
b1000 (
b1000 #
b1000 '
b1000 %
#2490
b1001 (
b1001 #
b1001 '
b1001 %
#2500
b1010 (
b1010 #
b1010 '
b1010 %
#2510
b1011 (
b1011 #
b1011 '
b1011 %
#2520
b1100 (
b1100 #
b1100 '
b1100 %
#2530
b1101 (
b1101 #
b1101 '
b1101 %
#2540
b1110 (
b1110 #
b1110 '
b1110 %
#2550
1!
b1111 (
b1111 #
b1111 '
b1111 %
#2560
b10000 $
b10000 %
