fsm-assignments/ problem3_vending/vending_mealy.v
module vending_mealy(
    input wire clk,
    input wire rst,        // synchronous active-high
    input wire [1:0] coin, // 01=5, 10=10, 00=idle
    output reg dispense,   // 1-cycle pulse
    output reg chg5        // 1-cycle pulse when returning 5
);

    // State encoding using parameters
    parameter S0  = 2'b00;  // total = 0
    parameter S5  = 2'b01;  // total = 5
    parameter S10 = 2'b10;  // total = 10
    parameter S15 = 2'b11;  // total = 15

    reg [1:0] state, next_state;
    reg [1:0] coin_d;   

    wire coin_edge = (coin != 2'b00) && (coin_d == 2'b00);

    
    always @(*) begin
        
        dispense = 0;
        chg5 = 0;
        next_state = state;

        case (state)
            S0: begin
                if (coin_edge && coin == 2'b01) next_state = S5;
                else if (coin_edge && coin == 2'b10) next_state = S10;
            end

            S5: begin
                if (coin_edge && coin == 2'b01) next_state = S10;
                else if (coin_edge && coin == 2'b10) next_state = S15;
            end

            S10: begin
                if (coin_edge && coin == 2'b01) next_state = S15;
                else if (coin_edge && coin == 2'b10) begin
                    dispense = 1;
                    next_state = S0;
                end
            end

            S15: begin
                if (coin_edge && coin == 2'b01) begin
                    dispense = 1;
                    next_state = S0;
                end else if (coin_edge && coin == 2'b10) begin
                    dispense = 1;
                    chg5 = 1;
                    next_state = S0;
                end
            end
        endcase
    end

    always @(posedge clk) begin
        if (rst) begin
            state  <= S0;
            coin_d <= 2'b00;
        end else begin
            state  <= next_state;
            coin_d <= coin;   
        end
    end


endmodule

fsm-assignments/ problem3_vending/tb_vending_mealy.v
module tb_vending_mealy;
    reg clk, rst;
    reg [1:0] coin;
    wire dispense, chg5;

    
    vending_mealy dut(.clk(clk), .rst(rst), .coin(coin),
                      .dispense(dispense), .chg5(chg5));

    
    always #5 clk = ~clk;

    initial begin
        // VCD Dump setup
        $dumpfile("vending_mealy.vcd");   
        $dumpvars(0, tb_vending_mealy);   

       
        clk = 0; rst = 1; coin = 2'b00;
        #11 rst = 0;

        
        #10 coin = 2'b01; #10 coin = 2'b00;
        #10 coin = 2'b01; #10 coin = 2'b00;
        #10 coin = 2'b10; #10 coin = 2'b00;

       
        #10 coin = 2'b10; #10 coin = 2'b00;
        #10 coin = 2'b01; #10 coin = 2'b00;
        #10 coin = 2'b10; #10 coin = 2'b00;

       
        #10 coin = 2'b10; #10 coin = 2'b00;
        #10 coin = 2'b01; #10 coin = 2'b00;
        #10 coin = 2'b01; #10 coin = 2'b00;

        #50 $finish;
    end
    initial begin
    $monitor("T=%0t | state=%b | coin=%b | dispense=%b | chg5=%b", 
              $time, dut.state, coin, dispense, chg5);
end

endmodule

fsm-assignments/ problem3_vending/vending_mealy.vcd
$date
	Sun Aug 17 22:23:11 2025
$end
$version
	Icarus Verilog
$end
$timescale
	1s
$end
$scope module tb_vending_mealy $end
$var wire 1 ! dispense $end
$var wire 1 " chg5 $end
$var reg 1 # clk $end
$var reg 2 $ coin [1:0] $end
$var reg 1 % rst $end
$scope module dut $end
$var wire 1 # clk $end
$var wire 2 & coin [1:0] $end
$var wire 1 ' coin_edge $end
$var wire 1 % rst $end
$var parameter 2 ( S0 $end
$var parameter 2 ) S10 $end
$var parameter 2 * S15 $end
$var parameter 2 + S5 $end
$var reg 1 " chg5 $end
$var reg 2 , coin_d [1:0] $end
$var reg 1 ! dispense $end
$var reg 2 - next_state [1:0] $end
$var reg 2 . state [1:0] $end
$upscope $end
$upscope $end
$enddefinitions $end
$comment Show the parameter values. $end
$dumpall
b1 +
b11 *
b10 )
b0 (
$end
#0
$dumpvars
bx .
bx -
bx ,
0'
b0 &
1%
b0 $
0#
0"
0!
$end
#5
b0 -
b0 ,
b0 .
1#
#10
0#
#11
0%
#15
1#
#20
0#
#21
b1 -
1'
b1 $
b1 &
#25
0'
b1 -
b1 ,
b1 .
1#
#30
0#
#31
b0 $
b0 &
#35
b0 ,
1#
#40
0#
#41
b10 -
1'
b1 $
b1 &
#45
0'
b10 -
b1 ,
b10 .
1#
#50
0#
#51
b0 $
b0 &
#55
b0 ,
1#
#60
0#
#61
b0 -
1!
1'
b10 $
b10 &
#65
0'
b0 -
0!
b10 ,
b0 .
1#
#70
0#
#71
b0 $
b0 &
#75
b0 ,
1#
#80
0#
#81
b10 -
1'
b10 $
b10 &
#85
0'
b10 -
0!
b10 ,
b10 .
1#
#90
0#
#91
b0 $
b0 &
#95
b0 ,
1#
#100
0#
#101
b11 -
1'
b1 $
b1 &
#105
0'
b11 -
0!
b1 ,
b11 .
1#
#110
0#
#111
b0 $
b0 &
#115
b0 ,
1#
#120
0#
#121
b0 -
1"
1!
1'
b10 $
b10 &
#125
0'
b0 -
0"
0!
b10 ,
b0 .
1#
#130
0#
#131
b0 $
b0 &
#135
b0 ,
1#
#140
0#
#141
b10 -
1'
b10 $
b10 &
#145
0'
b10 -
0!
b10 ,
b10 .
1#
#150
0#
#151
b0 $
b0 &
#155
b0 ,
1#
#160
0#
#161
b11 -
1'
b1 $
b1 &
#165
0'
b11 -
0!
b1 ,
b11 .
1#
#170
0#
#171
b0 $
b0 &
#175
b0 ,
1#
#180
0#
#181
b0 -
1!
1'
b1 $
b1 &
#185
0'
b0 -
0!
b1 ,
b0 .
1#
#190
0#
#191
b0 $
b0 &
#195
b0 ,
1#
